{"nodes": [{"id": "c_users_aditya_rane_downloads_faraway_hackathon_backend_services_whisper_service_py", "label": "whisper_service.py", "file_type": "code", "source_file": "C:\\Users\\Aditya Rane\\Downloads\\FarAway Hackathon\\backend\\services\\whisper_service.py", "source_location": "L1"}, {"id": "services_whisper_service_get_local_model", "label": "_get_local_model()", "file_type": "code", "source_file": "C:\\Users\\Aditya Rane\\Downloads\\FarAway Hackathon\\backend\\services\\whisper_service.py", "source_location": "L29"}, {"id": "services_whisper_service_groq_transcribe", "label": "_groq_transcribe()", "file_type": "code", "source_file": "C:\\Users\\Aditya Rane\\Downloads\\FarAway Hackathon\\backend\\services\\whisper_service.py", "source_location": "L85"}, {"id": "services_whisper_service_local_transcribe", "label": "_local_transcribe()", "file_type": "code", "source_file": "C:\\Users\\Aditya Rane\\Downloads\\FarAway Hackathon\\backend\\services\\whisper_service.py", "source_location": "L133"}, {"id": "services_whisper_service_transcribe_audio", "label": "transcribe_audio()", "file_type": "code", "source_file": "C:\\Users\\Aditya Rane\\Downloads\\FarAway Hackathon\\backend\\services\\whisper_service.py", "source_location": "L157"}, {"id": "services_whisper_service_preload_model", "label": "preload_model()", "file_type": "code", "source_file": "C:\\Users\\Aditya Rane\\Downloads\\FarAway Hackathon\\backend\\services\\whisper_service.py", "source_location": "L176"}, {"id": "services_whisper_service_rationale_30", "label": "Lazy-load faster-whisper model (only used as last resort).", "file_type": "rationale", "source_file": "C:\\Users\\Aditya Rane\\Downloads\\FarAway Hackathon\\backend\\services\\whisper_service.py", "source_location": "L30"}, {"id": "services_whisper_service_rationale_86", "label": "Transcribe via Groq Whisper-large-v3 cloud API with retry.", "file_type": "rationale", "source_file": "C:\\Users\\Aditya Rane\\Downloads\\FarAway Hackathon\\backend\\services\\whisper_service.py", "source_location": "L86"}, {"id": "services_whisper_service_rationale_134", "label": "Fallback: transcribe locally with faster-whisper.", "file_type": "rationale", "source_file": "C:\\Users\\Aditya Rane\\Downloads\\FarAway Hackathon\\backend\\services\\whisper_service.py", "source_location": "L134"}, {"id": "services_whisper_service_rationale_158", "label": "Transcribe audio file to text.     Strategy:       1. If GROQ_API_KEY is set \u2192 u", "file_type": "rationale", "source_file": "C:\\Users\\Aditya Rane\\Downloads\\FarAway Hackathon\\backend\\services\\whisper_service.py", "source_location": "L158"}, {"id": "services_whisper_service_rationale_177", "label": "Preloads the local model into memory if local inference is enabled.     This pre", "file_type": "rationale", "source_file": "C:\\Users\\Aditya Rane\\Downloads\\FarAway Hackathon\\backend\\services\\whisper_service.py", "source_location": "L177"}], "edges": [{"source": "c_users_aditya_rane_downloads_faraway_hackathon_backend_services_whisper_service_py", "target": "httpx", "relation": "imports", "context": "import", "confidence": "EXTRACTED", "source_file": "C:\\Users\\Aditya Rane\\Downloads\\FarAway Hackathon\\backend\\services\\whisper_service.py", "source_location": "L1", "weight": 1.0}, {"source": "c_users_aditya_rane_downloads_faraway_hackathon_backend_services_whisper_service_py", "target": "os", "relation": "imports", "context": "import", "confidence": "EXTRACTED", "source_file": "C:\\Users\\Aditya Rane\\Downloads\\FarAway Hackathon\\backend\\services\\whisper_service.py", "source_location": "L2", "weight": 1.0}, {"source": "c_users_aditya_rane_downloads_faraway_hackathon_backend_services_whisper_service_py", "target": "time", "relation": "imports", "context": "import", "confidence": "EXTRACTED", "source_file": "C:\\Users\\Aditya Rane\\Downloads\\FarAway Hackathon\\backend\\services\\whisper_service.py", "source_location": "L3", "weight": 1.0}, {"source": "c_users_aditya_rane_downloads_faraway_hackathon_backend_services_whisper_service_py", "target": "asyncio", "relation": "imports", "context": "import", "confidence": "EXTRACTED", "source_file": "C:\\Users\\Aditya Rane\\Downloads\\FarAway Hackathon\\backend\\services\\whisper_service.py", "source_location": "L4", "weight": 1.0}, {"source": "c_users_aditya_rane_downloads_faraway_hackathon_backend_services_whisper_service_py", "target": "logging", "relation": "imports", "context": "import", "confidence": "EXTRACTED", "source_file": "C:\\Users\\Aditya Rane\\Downloads\\FarAway Hackathon\\backend\\services\\whisper_service.py", "source_location": "L5", "weight": 1.0}, {"source": "c_users_aditya_rane_downloads_faraway_hackathon_backend_services_whisper_service_py", "target": "services_whisper_service_get_local_model", "relation": "contains", "confidence": "EXTRACTED", "source_file": "C:\\Users\\Aditya Rane\\Downloads\\FarAway Hackathon\\backend\\services\\whisper_service.py", "source_location": "L29", "weight": 1.0}, {"source": "c_users_aditya_rane_downloads_faraway_hackathon_backend_services_whisper_service_py", "target": "services_whisper_service_groq_transcribe", "relation": "contains", "confidence": "EXTRACTED", "source_file": "C:\\Users\\Aditya Rane\\Downloads\\FarAway Hackathon\\backend\\services\\whisper_service.py", "source_location": "L85", "weight": 1.0}, {"source": "c_users_aditya_rane_downloads_faraway_hackathon_backend_services_whisper_service_py", "target": "services_whisper_service_local_transcribe", "relation": "contains", "confidence": "EXTRACTED", "source_file": "C:\\Users\\Aditya Rane\\Downloads\\FarAway Hackathon\\backend\\services\\whisper_service.py", "source_location": "L133", "weight": 1.0}, {"source": "c_users_aditya_rane_downloads_faraway_hackathon_backend_services_whisper_service_py", "target": "services_whisper_service_transcribe_audio", "relation": "contains", "confidence": "EXTRACTED", "source_file": "C:\\Users\\Aditya Rane\\Downloads\\FarAway Hackathon\\backend\\services\\whisper_service.py", "source_location": "L157", "weight": 1.0}, {"source": "c_users_aditya_rane_downloads_faraway_hackathon_backend_services_whisper_service_py", "target": "services_whisper_service_preload_model", "relation": "contains", "confidence": "EXTRACTED", "source_file": "C:\\Users\\Aditya Rane\\Downloads\\FarAway Hackathon\\backend\\services\\whisper_service.py", "source_location": "L176", "weight": 1.0}, {"source": "services_whisper_service_transcribe_audio", "target": "services_whisper_service_groq_transcribe", "relation": "calls", "context": "call", "confidence": "EXTRACTED", "source_file": "C:\\Users\\Aditya Rane\\Downloads\\FarAway Hackathon\\backend\\services\\whisper_service.py", "source_location": "L166", "weight": 1.0}, {"source": "services_whisper_service_transcribe_audio", "target": "services_whisper_service_local_transcribe", "relation": "calls", "context": "call", "confidence": "EXTRACTED", "source_file": "C:\\Users\\Aditya Rane\\Downloads\\FarAway Hackathon\\backend\\services\\whisper_service.py", "source_location": "L174", "weight": 1.0}, {"source": "services_whisper_service_preload_model", "target": "services_whisper_service_get_local_model", "relation": "calls", "context": "call", "confidence": "EXTRACTED", "source_file": "C:\\Users\\Aditya Rane\\Downloads\\FarAway Hackathon\\backend\\services\\whisper_service.py", "source_location": "L183", "weight": 1.0}, {"source": "services_whisper_service_rationale_30", "target": "services_whisper_service_get_local_model", "relation": "rationale_for", "confidence": "EXTRACTED", "source_file": "C:\\Users\\Aditya Rane\\Downloads\\FarAway Hackathon\\backend\\services\\whisper_service.py", "source_location": "L30", "weight": 1.0}, {"source": "services_whisper_service_rationale_86", "target": "services_whisper_service_groq_transcribe", "relation": "rationale_for", "confidence": "EXTRACTED", "source_file": "C:\\Users\\Aditya Rane\\Downloads\\FarAway Hackathon\\backend\\services\\whisper_service.py", "source_location": "L86", "weight": 1.0}, {"source": "services_whisper_service_rationale_134", "target": "services_whisper_service_local_transcribe", "relation": "rationale_for", "confidence": "EXTRACTED", "source_file": "C:\\Users\\Aditya Rane\\Downloads\\FarAway Hackathon\\backend\\services\\whisper_service.py", "source_location": "L134", "weight": 1.0}, {"source": "services_whisper_service_rationale_158", "target": "services_whisper_service_transcribe_audio", "relation": "rationale_for", "confidence": "EXTRACTED", "source_file": "C:\\Users\\Aditya Rane\\Downloads\\FarAway Hackathon\\backend\\services\\whisper_service.py", "source_location": "L158", "weight": 1.0}, {"source": "services_whisper_service_rationale_177", "target": "services_whisper_service_preload_model", "relation": "rationale_for", "confidence": "EXTRACTED", "source_file": "C:\\Users\\Aditya Rane\\Downloads\\FarAway Hackathon\\backend\\services\\whisper_service.py", "source_location": "L177", "weight": 1.0}], "raw_calls": [{"caller_nid": "services_whisper_service_get_local_model", "callee": "info", "is_member_call": true, "source_file": "C:\\Users\\Aditya Rane\\Downloads\\FarAway Hackathon\\backend\\services\\whisper_service.py", "source_location": "L34"}, {"caller_nid": "services_whisper_service_get_local_model", "callee": "time", "is_member_call": true, "source_file": "C:\\Users\\Aditya Rane\\Downloads\\FarAway Hackathon\\backend\\services\\whisper_service.py", "source_location": "L35"}, {"caller_nid": "services_whisper_service_get_local_model", "callee": "any", "is_member_call": false, "source_file": "C:\\Users\\Aditya Rane\\Downloads\\FarAway Hackathon\\backend\\services\\whisper_service.py", "source_location": "L39"}, {"caller_nid": "services_whisper_service_get_local_model", "callee": "get", "is_member_call": true, "source_file": "C:\\Users\\Aditya Rane\\Downloads\\FarAway Hackathon\\backend\\services\\whisper_service.py", "source_location": "L39"}, {"caller_nid": "services_whisper_service_get_local_model", "callee": "lower", "is_member_call": true, "source_file": "C:\\Users\\Aditya Rane\\Downloads\\FarAway Hackathon\\backend\\services\\whisper_service.py", "source_location": "L40"}, {"caller_nid": "services_whisper_service_get_local_model", "callee": "get", "is_member_call": true, "source_file": "C:\\Users\\Aditya Rane\\Downloads\\FarAway Hackathon\\backend\\services\\whisper_service.py", "source_location": "L40"}, {"caller_nid": "services_whisper_service_get_local_model", "callee": "info", "is_member_call": true, "source_file": "C:\\Users\\Aditya Rane\\Downloads\\FarAway Hackathon\\backend\\services\\whisper_service.py", "source_location": "L46"}, {"caller_nid": "services_whisper_service_get_local_model", "callee": "get_cuda_device_count", "is_member_call": true, "source_file": "C:\\Users\\Aditya Rane\\Downloads\\FarAway Hackathon\\backend\\services\\whisper_service.py", "source_location": "L50"}, {"caller_nid": "services_whisper_service_get_local_model", "callee": "info", "is_member_call": true, "source_file": "C:\\Users\\Aditya Rane\\Downloads\\FarAway Hackathon\\backend\\services\\whisper_service.py", "source_location": "L53"}, {"caller_nid": "services_whisper_service_get_local_model", "callee": "info", "is_member_call": true, "source_file": "C:\\Users\\Aditya Rane\\Downloads\\FarAway Hackathon\\backend\\services\\whisper_service.py", "source_location": "L55"}, {"caller_nid": "services_whisper_service_get_local_model", "callee": "warning", "is_member_call": true, "source_file": "C:\\Users\\Aditya Rane\\Downloads\\FarAway Hackathon\\backend\\services\\whisper_service.py", "source_location": "L57"}, {"caller_nid": "services_whisper_service_get_local_model", "callee": "info", "is_member_call": true, "source_file": "C:\\Users\\Aditya Rane\\Downloads\\FarAway Hackathon\\backend\\services\\whisper_service.py", "source_location": "L61"}, {"caller_nid": "services_whisper_service_get_local_model", "callee": "WhisperModel", "is_member_call": false, "source_file": "C:\\Users\\Aditya Rane\\Downloads\\FarAway Hackathon\\backend\\services\\whisper_service.py", "source_location": "L62"}, {"caller_nid": "services_whisper_service_get_local_model", "callee": "info", "is_member_call": true, "source_file": "C:\\Users\\Aditya Rane\\Downloads\\FarAway Hackathon\\backend\\services\\whisper_service.py", "source_location": "L63"}, {"caller_nid": "services_whisper_service_get_local_model", "callee": "time", "is_member_call": true, "source_file": "C:\\Users\\Aditya Rane\\Downloads\\FarAway Hackathon\\backend\\services\\whisper_service.py", "source_location": "L63"}, {"caller_nid": "services_whisper_service_get_local_model", "callee": "WhisperModel", "is_member_call": false, "source_file": "C:\\Users\\Aditya Rane\\Downloads\\FarAway Hackathon\\backend\\services\\whisper_service.py", "source_location": "L65"}, {"caller_nid": "services_whisper_service_get_local_model", "callee": "info", "is_member_call": true, "source_file": "C:\\Users\\Aditya Rane\\Downloads\\FarAway Hackathon\\backend\\services\\whisper_service.py", "source_location": "L66"}, {"caller_nid": "services_whisper_service_get_local_model", "callee": "time", "is_member_call": true, "source_file": "C:\\Users\\Aditya Rane\\Downloads\\FarAway Hackathon\\backend\\services\\whisper_service.py", "source_location": "L66"}, {"caller_nid": "services_whisper_service_get_local_model", "callee": "warning", "is_member_call": true, "source_file": "C:\\Users\\Aditya Rane\\Downloads\\FarAway Hackathon\\backend\\services\\whisper_service.py", "source_location": "L70"}, {"caller_nid": "services_whisper_service_get_local_model", "callee": "time", "is_member_call": true, "source_file": "C:\\Users\\Aditya Rane\\Downloads\\FarAway Hackathon\\backend\\services\\whisper_service.py", "source_location": "L71"}, {"caller_nid": "services_whisper_service_get_local_model", "callee": "WhisperModel", "is_member_call": false, "source_file": "C:\\Users\\Aditya Rane\\Downloads\\FarAway Hackathon\\backend\\services\\whisper_service.py", "source_location": "L72"}, {"caller_nid": "services_whisper_service_get_local_model", "callee": "info", "is_member_call": true, "source_file": "C:\\Users\\Aditya Rane\\Downloads\\FarAway Hackathon\\backend\\services\\whisper_service.py", "source_location": "L73"}, {"caller_nid": "services_whisper_service_get_local_model", "callee": "time", "is_member_call": true, "source_file": "C:\\Users\\Aditya Rane\\Downloads\\FarAway Hackathon\\backend\\services\\whisper_service.py", "source_location": "L73"}, {"caller_nid": "services_whisper_service_get_local_model", "callee": "error", "is_member_call": true, "source_file": "C:\\Users\\Aditya Rane\\Downloads\\FarAway Hackathon\\backend\\services\\whisper_service.py", "source_location": "L75"}, {"caller_nid": "services_whisper_service_get_local_model", "callee": "RuntimeError", "is_member_call": false, "source_file": "C:\\Users\\Aditya Rane\\Downloads\\FarAway Hackathon\\backend\\services\\whisper_service.py", "source_location": "L76"}, {"caller_nid": "services_whisper_service_groq_transcribe", "callee": "lower", "is_member_call": true, "source_file": "C:\\Users\\Aditya Rane\\Downloads\\FarAway Hackathon\\backend\\services\\whisper_service.py", "source_location": "L87"}, {"caller_nid": "services_whisper_service_groq_transcribe", "callee": "splitext", "is_member_call": true, "source_file": "C:\\Users\\Aditya Rane\\Downloads\\FarAway Hackathon\\backend\\services\\whisper_service.py", "source_location": "L87"}, {"caller_nid": "services_whisper_service_groq_transcribe", "callee": "get", "is_member_call": true, "source_file": "C:\\Users\\Aditya Rane\\Downloads\\FarAway Hackathon\\backend\\services\\whisper_service.py", "source_location": "L88"}, {"caller_nid": "services_whisper_service_groq_transcribe", "callee": "basename", "is_member_call": true, "source_file": "C:\\Users\\Aditya Rane\\Downloads\\FarAway Hackathon\\backend\\services\\whisper_service.py", "source_location": "L89"}, {"caller_nid": "services_whisper_service_groq_transcribe", "callee": "time", "is_member_call": true, "source_file": "C:\\Users\\Aditya Rane\\Downloads\\FarAway Hackathon\\backend\\services\\whisper_service.py", "source_location": "L92"}, {"caller_nid": "services_whisper_service_groq_transcribe", "callee": "range", "is_member_call": false, "source_file": "C:\\Users\\Aditya Rane\\Downloads\\FarAway Hackathon\\backend\\services\\whisper_service.py", "source_location": "L93"}, {"caller_nid": "services_whisper_service_groq_transcribe", "callee": "info", "is_member_call": true, "source_file": "C:\\Users\\Aditya Rane\\Downloads\\FarAway Hackathon\\backend\\services\\whisper_service.py", "source_location": "L95"}, {"caller_nid": "services_whisper_service_groq_transcribe", "callee": "open", "is_member_call": false, "source_file": "C:\\Users\\Aditya Rane\\Downloads\\FarAway Hackathon\\backend\\services\\whisper_service.py", "source_location": "L96"}, {"caller_nid": "services_whisper_service_groq_transcribe", "callee": "post", "is_member_call": true, "source_file": "C:\\Users\\Aditya Rane\\Downloads\\FarAway Hackathon\\backend\\services\\whisper_service.py", "source_location": "L97"}, {"caller_nid": "services_whisper_service_groq_transcribe", "callee": "raise_for_status", "is_member_call": true, "source_file": "C:\\Users\\Aditya Rane\\Downloads\\FarAway Hackathon\\backend\\services\\whisper_service.py", "source_location": "L107"}, {"caller_nid": "services_whisper_service_groq_transcribe", "callee": "strip", "is_member_call": true, "source_file": "C:\\Users\\Aditya Rane\\Downloads\\FarAway Hackathon\\backend\\services\\whisper_service.py", "source_location": "L108"}, {"caller_nid": "services_whisper_service_groq_transcribe", "callee": "get", "is_member_call": true, "source_file": "C:\\Users\\Aditya Rane\\Downloads\\FarAway Hackathon\\backend\\services\\whisper_service.py", "source_location": "L108"}, {"caller_nid": "services_whisper_service_groq_transcribe", "callee": "json", "is_member_call": true, "source_file": "C:\\Users\\Aditya Rane\\Downloads\\FarAway Hackathon\\backend\\services\\whisper_service.py", "source_location": "L108"}, {"caller_nid": "services_whisper_service_groq_transcribe", "callee": "time", "is_member_call": true, "source_file": "C:\\Users\\Aditya Rane\\Downloads\\FarAway Hackathon\\backend\\services\\whisper_service.py", "source_location": "L109"}, {"caller_nid": "services_whisper_service_groq_transcribe", "callee": "len", "is_member_call": false, "source_file": "C:\\Users\\Aditya Rane\\Downloads\\FarAway Hackathon\\backend\\services\\whisper_service.py", "source_location": "L110"}, {"caller_nid": "services_whisper_service_groq_transcribe", "callee": "info", "is_member_call": true, "source_file": "C:\\Users\\Aditya Rane\\Downloads\\FarAway Hackathon\\backend\\services\\whisper_service.py", "source_location": "L111"}, {"caller_nid": "services_whisper_service_groq_transcribe", "callee": "error", "is_member_call": true, "source_file": "C:\\Users\\Aditya Rane\\Downloads\\FarAway Hackathon\\backend\\services\\whisper_service.py", "source_location": "L120"}, {"caller_nid": "services_whisper_service_groq_transcribe", "callee": "sleep", "is_member_call": true, "source_file": "C:\\Users\\Aditya Rane\\Downloads\\FarAway Hackathon\\backend\\services\\whisper_service.py", "source_location": "L123"}, {"caller_nid": "services_whisper_service_groq_transcribe", "callee": "warning", "is_member_call": true, "source_file": "C:\\Users\\Aditya Rane\\Downloads\\FarAway Hackathon\\backend\\services\\whisper_service.py", "source_location": "L126"}, {"caller_nid": "services_whisper_service_groq_transcribe", "callee": "sleep", "is_member_call": true, "source_file": "C:\\Users\\Aditya Rane\\Downloads\\FarAway Hackathon\\backend\\services\\whisper_service.py", "source_location": "L127"}, {"caller_nid": "services_whisper_service_groq_transcribe", "callee": "error", "is_member_call": true, "source_file": "C:\\Users\\Aditya Rane\\Downloads\\FarAway Hackathon\\backend\\services\\whisper_service.py", "source_location": "L129"}, {"caller_nid": "services_whisper_service_groq_transcribe", "callee": "RuntimeError", "is_member_call": false, "source_file": "C:\\Users\\Aditya Rane\\Downloads\\FarAway Hackathon\\backend\\services\\whisper_service.py", "source_location": "L130"}, {"caller_nid": "services_whisper_service_local_transcribe", "callee": "info", "is_member_call": true, "source_file": "C:\\Users\\Aditya Rane\\Downloads\\FarAway Hackathon\\backend\\services\\whisper_service.py", "source_location": "L135"}, {"caller_nid": "services_whisper_service_local_transcribe", "callee": "time", "is_member_call": true, "source_file": "C:\\Users\\Aditya Rane\\Downloads\\FarAway Hackathon\\backend\\services\\whisper_service.py", "source_location": "L136"}, {"caller_nid": "services_whisper_service_local_transcribe", "callee": "to_thread", "is_member_call": true, "source_file": "C:\\Users\\Aditya Rane\\Downloads\\FarAway Hackathon\\backend\\services\\whisper_service.py", "source_location": "L144"}, {"caller_nid": "services_whisper_service_local_transcribe", "callee": "time", "is_member_call": true, "source_file": "C:\\Users\\Aditya Rane\\Downloads\\FarAway Hackathon\\backend\\services\\whisper_service.py", "source_location": "L145"}, {"caller_nid": "services_whisper_service_local_transcribe", "callee": "len", "is_member_call": false, "source_file": "C:\\Users\\Aditya Rane\\Downloads\\FarAway Hackathon\\backend\\services\\whisper_service.py", "source_location": "L147"}, {"caller_nid": "services_whisper_service_local_transcribe", "callee": "info", "is_member_call": true, "source_file": "C:\\Users\\Aditya Rane\\Downloads\\FarAway Hackathon\\backend\\services\\whisper_service.py", "source_location": "L148"}, {"caller_nid": "services_whisper_service_local_transcribe", "callee": "round", "is_member_call": false, "source_file": "C:\\Users\\Aditya Rane\\Downloads\\FarAway Hackathon\\backend\\services\\whisper_service.py", "source_location": "L152"}, {"caller_nid": "services_whisper_service_transcribe_audio", "callee": "error", "is_member_call": true, "source_file": "C:\\Users\\Aditya Rane\\Downloads\\FarAway Hackathon\\backend\\services\\whisper_service.py", "source_location": "L168"}, {"caller_nid": "services_whisper_service_transcribe_audio", "callee": "RuntimeError", "is_member_call": false, "source_file": "C:\\Users\\Aditya Rane\\Downloads\\FarAway Hackathon\\backend\\services\\whisper_service.py", "source_location": "L169"}, {"caller_nid": "services_whisper_service_preload_model", "callee": "info", "is_member_call": true, "source_file": "C:\\Users\\Aditya Rane\\Downloads\\FarAway Hackathon\\backend\\services\\whisper_service.py", "source_location": "L181"}, {"caller_nid": "services_whisper_service_preload_model", "callee": "info", "is_member_call": true, "source_file": "C:\\Users\\Aditya Rane\\Downloads\\FarAway Hackathon\\backend\\services\\whisper_service.py", "source_location": "L184"}, {"caller_nid": "services_whisper_service_preload_model", "callee": "error", "is_member_call": true, "source_file": "C:\\Users\\Aditya Rane\\Downloads\\FarAway Hackathon\\backend\\services\\whisper_service.py", "source_location": "L186"}]}